iclib/__init__.py
iclib/a1230.py
iclib/adc78h89.py
iclib/bno055.py
iclib/ina229.py
iclib/lis2ds12.py
iclib/ltc6810.py
iclib/mcp23s17.py
iclib/mcp4161.py
iclib/nau7802.py
iclib/nhd_c12864a1z_fsw_fbw_htt.py
iclib/pa1616s.py
iclib/pca9546adr.py
iclib/py.typed
iclib/rotary_encoder.py
iclib/sn74hcs137.py
iclib/tmag5273.py
iclib/utilities.py
iclib/wavesculptor22.py
iclib/tests/__init__.py
iclib/tests/test_adc78h89.py
iclib/tests/test_bno055.py
iclib/tests/test_ina229.py
iclib/tests/test_lis2ds12.py
iclib/tests/test_ltc6810.py
iclib/tests/test_mcp23s17.py
iclib/tests/test_mcp4161.py
iclib/tests/test_sn74hcs137.py
iclib/tests/test_wavesculptor22.py
iclib-0.0.0.dev21.dist-info/LICENSE
iclib-0.0.0.dev21.dist-info/METADATA
iclib-0.0.0.dev21.dist-info/WHEEL
iclib-0.0.0.dev21.dist-info/top_level.txt
iclib-0.0.0.dev21.dist-info/RECORD
