Metadata-Version: 2.1
Name: iclib
Version: 0.0.0.dev21
Summary: A collection of integrated circuit libraries in pure Python
Home-page: https://github.com/blueskysolarracing/iclib
Author: Blue Sky Solar Racing
Author-email: blueskysolar@studentorg.utoronto.ca
License: MIT
Project-URL: Documentation, https://iclib.readthedocs.io/en/latest/
Project-URL: Source, https://github.com/blueskysolarracing/iclib
Project-URL: Tracker, https://github.com/blueskysolarracing/iclib/issues
Keywords: a1230,adc78h89,ina229,lis2ds12,ltc6810,mcp23s17,mcp4161,microchip technology,nau7802,newhaven display,nhd-c12864a1z-fsw-fbw-htt,pa1616s,pca9546adr,python,sn74hcs137,texas instruments,ti,tmag5273
Classifier: Development Status :: 5 - Production/Stable
Classifier: Intended Audience :: Developers
Classifier: Intended Audience :: Education
Classifier: Topic :: Education
Classifier: Topic :: Scientific/Engineering
Classifier: License :: OSI Approved :: MIT License
Classifier: Operating System :: OS Independent
Classifier: Programming Language :: Python
Classifier: Programming Language :: Python :: 3
Classifier: Programming Language :: Python :: 3 :: Only
Classifier: Programming Language :: Python :: 3.11
Classifier: Programming Language :: Python :: 3.12
Requires-Python: >=3.11
License-File: LICENSE
Requires-Dist: python-periphery <3,>=2.4.0
Requires-Dist: freetype-py <3,>=2.4.0
